boris/__init__.py
boris/cli/__init__.py
boris/cli/_helpers.py
boris/cli/boris_cli.py
boris/cli/download_cli.py
boris/cli/embed_cli.py
boris/cli/train_cli.py
boris/cli/upload_cli.py
borisml-1.0.0.dist-info/LICENSE.txt
borisml-1.0.0.dist-info/METADATA
borisml-1.0.0.dist-info/WHEEL
borisml-1.0.0.dist-info/entry_points.txt
borisml-1.0.0.dist-info/top_level.txt
borisml-1.0.0.dist-info/RECORD
